{"domain": "S_both", "action": "v_wavelet", "model": "chronos_bolt_small", "menu_sha": "a4c0f83191e5bd18fb8b7b9f52854e356268ef3cf0e7e3420e3a0221514db457", "train_cfg_sha": "812a71fdd8764baa", "n": 84, "n_missing": 0, "wallclock_s": 0.2, "cache_keys": {"S2:S_both:n_hi_block_hi:0": "b71075582fa9026b"}, "per_series": {"S2:S_both:n_hi_block_hi:0": 1.37175, "S2:S_both:n_hi_block_hi:1": 0.430699, "S2:S_both:n_hi_block_hi:2": 0.238969, "S2:S_both:n_hi_block_hi:3": 0.323255, "S2:S_both:n_hi_block_hi:6": 0.600285, "S2:S_both:n_hi_block_hi:7": 0.317127, "S2:S_both:n_hi_block_hi:8": 0.273017, "S2:S_both:n_hi_block_lo:0": 0.304754, "S2:S_both:n_hi_block_lo:1": 0.23893, "S2:S_both:n_hi_block_lo:2": 0.301318, "S2:S_both:n_hi_block_lo:4": 0.394543, "S2:S_both:n_hi_block_lo:6": 0.254461, "S2:S_both:n_hi_block_lo:7": 0.373926, "S2:S_both:n_hi_block_lo:8": 0.299546, "S2:S_both:n_hi_burst:0": 0.274291, "S2:S_both:n_hi_burst:2": 0.370488, "S2:S_both:n_hi_burst:4": 0.278873, "S2:S_both:n_hi_burst:6": 0.521725, "S2:S_both:n_hi_burst:7": 0.361313, "S2:S_both:n_hi_burst:8": 0.262296, "S2:S_both:n_hi_burst:9": 7.896127, "S2:S_both:n_hi_full:0": 0.412572, "S2:S_both:n_hi_full:1": 0.297824, "S2:S_both:n_hi_full:2": 0.318835, "S2:S_both:n_hi_full:3": 0.281321, "S2:S_both:n_hi_full:4": 0.350927, "S2:S_both:n_hi_full:5": 0.273509, "S2:S_both:n_hi_full:7": 0.201425, "S2:S_both:n_hi_rand_hi:0": 0.553838, "S2:S_both:n_hi_rand_hi:1": 0.305882, "S2:S_both:n_hi_rand_hi:2": 0.218947, "S2:S_both:n_hi_rand_hi:4": 0.379787, "S2:S_both:n_hi_rand_hi:6": 0.22927, "S2:S_both:n_hi_rand_hi:8": 0.277551, "S2:S_both:n_hi_rand_hi:9": 0.299902, "S2:S_both:n_hi_rand_lo:1": 0.256856, "S2:S_both:n_hi_rand_lo:2": 0.252489, "S2:S_both:n_hi_rand_lo:3": 0.247528, "S2:S_both:n_hi_rand_lo:4": 0.300137, "S2:S_both:n_hi_rand_lo:5": 0.33876, "S2:S_both:n_hi_rand_lo:7": 0.404426, "S2:S_both:n_hi_rand_lo:9": 0.358503, "S2:S_both:n_lo_block_hi:0": 0.706515, "S2:S_both:n_lo_block_hi:3": 0.449338, "S2:S_both:n_lo_block_hi:4": 0.701513, "S2:S_both:n_lo_block_hi:5": 0.569427, "S2:S_both:n_lo_block_hi:6": 1.938431, "S2:S_both:n_lo_block_hi:7": 0.976153, "S2:S_both:n_lo_block_hi:8": 0.426859, "S2:S_both:n_lo_block_lo:0": 1.001367, "S2:S_both:n_lo_block_lo:1": 0.787126, "S2:S_both:n_lo_block_lo:2": 0.742688, "S2:S_both:n_lo_block_lo:3": 0.594573, "S2:S_both:n_lo_block_lo:4": 0.802615, "S2:S_both:n_lo_block_lo:5": 0.496438, "S2:S_both:n_lo_block_lo:8": 0.322735, "S2:S_both:n_lo_burst:0": 0.511884, "S2:S_both:n_lo_burst:3": 0.614822, "S2:S_both:n_lo_burst:4": 0.354932, "S2:S_both:n_lo_burst:5": 0.364248, "S2:S_both:n_lo_burst:6": 0.840834, "S2:S_both:n_lo_burst:7": 0.575076, "S2:S_both:n_lo_burst:8": 0.702536, "S2:S_both:n_lo_full:0": 0.32424, "S2:S_both:n_lo_full:1": 0.845888, "S2:S_both:n_lo_full:2": 0.494459, "S2:S_both:n_lo_full:4": 0.760863, "S2:S_both:n_lo_full:5": 0.605145, "S2:S_both:n_lo_full:7": 0.508445, "S2:S_both:n_lo_full:8": 0.520215, "S2:S_both:n_lo_rand_hi:0": 0.399917, "S2:S_both:n_lo_rand_hi:1": 2.504984, "S2:S_both:n_lo_rand_hi:2": 0.36479, "S2:S_both:n_lo_rand_hi:3": 0.509924, "S2:S_both:n_lo_rand_hi:4": 0.473108, "S2:S_both:n_lo_rand_hi:5": 0.438575, "S2:S_both:n_lo_rand_hi:9": 0.772779, "S2:S_both:n_lo_rand_lo:1": 1.022732, "S2:S_both:n_lo_rand_lo:2": 2.872887, "S2:S_both:n_lo_rand_lo:5": 1.308368, "S2:S_both:n_lo_rand_lo:6": 1.471555, "S2:S_both:n_lo_rand_lo:7": 0.337652, "S2:S_both:n_lo_rand_lo:8": 0.573132, "S2:S_both:n_lo_rand_lo:9": 1.444922}}