{"domain": "S_both", "action": "v_savgol", "model": "chronos_bolt_small", "menu_sha": "a4c0f83191e5bd18fb8b7b9f52854e356268ef3cf0e7e3420e3a0221514db457", "train_cfg_sha": "812a71fdd8764baa", "n": 84, "n_missing": 0, "wallclock_s": 0.2, "cache_keys": {"S2:S_both:n_hi_block_hi:0": "0bf5cf7d7fb9b6a2"}, "per_series": {"S2:S_both:n_hi_block_hi:0": 1.586198, "S2:S_both:n_hi_block_hi:1": 0.27128, "S2:S_both:n_hi_block_hi:2": 0.304247, "S2:S_both:n_hi_block_hi:3": 0.219406, "S2:S_both:n_hi_block_hi:6": 0.455057, "S2:S_both:n_hi_block_hi:7": 0.278815, "S2:S_both:n_hi_block_hi:8": 0.362994, "S2:S_both:n_hi_block_lo:0": 0.566787, "S2:S_both:n_hi_block_lo:1": 0.260336, "S2:S_both:n_hi_block_lo:2": 0.134015, "S2:S_both:n_hi_block_lo:4": 0.130393, "S2:S_both:n_hi_block_lo:6": 0.254452, "S2:S_both:n_hi_block_lo:7": 0.128278, "S2:S_both:n_hi_block_lo:8": 0.463927, "S2:S_both:n_hi_burst:0": 0.332679, "S2:S_both:n_hi_burst:2": 0.305357, "S2:S_both:n_hi_burst:4": 0.270053, "S2:S_both:n_hi_burst:6": 0.407885, "S2:S_both:n_hi_burst:7": 0.284759, "S2:S_both:n_hi_burst:8": 0.229926, "S2:S_both:n_hi_burst:9": 7.838051, "S2:S_both:n_hi_full:0": 0.34109, "S2:S_both:n_hi_full:1": 0.169785, "S2:S_both:n_hi_full:2": 0.300852, "S2:S_both:n_hi_full:3": 0.192392, "S2:S_both:n_hi_full:4": 0.142765, "S2:S_both:n_hi_full:5": 0.211353, "S2:S_both:n_hi_full:7": 0.329944, "S2:S_both:n_hi_rand_hi:0": 0.551199, "S2:S_both:n_hi_rand_hi:1": 0.29512, "S2:S_both:n_hi_rand_hi:2": 0.227084, "S2:S_both:n_hi_rand_hi:4": 0.80877, "S2:S_both:n_hi_rand_hi:6": 0.297262, "S2:S_both:n_hi_rand_hi:8": 0.204099, "S2:S_both:n_hi_rand_hi:9": 0.552838, "S2:S_both:n_hi_rand_lo:1": 0.13779, "S2:S_both:n_hi_rand_lo:2": 0.183516, "S2:S_both:n_hi_rand_lo:3": 0.166691, "S2:S_both:n_hi_rand_lo:4": 0.339368, "S2:S_both:n_hi_rand_lo:5": 1.661488, "S2:S_both:n_hi_rand_lo:7": 0.202364, "S2:S_both:n_hi_rand_lo:9": 1.461656, "S2:S_both:n_lo_block_hi:0": 1.111689, "S2:S_both:n_lo_block_hi:3": 0.695584, "S2:S_both:n_lo_block_hi:4": 0.749736, "S2:S_both:n_lo_block_hi:5": 0.864955, "S2:S_both:n_lo_block_hi:6": 1.468498, "S2:S_both:n_lo_block_hi:7": 1.082212, "S2:S_both:n_lo_block_hi:8": 0.475352, "S2:S_both:n_lo_block_lo:0": 0.758297, "S2:S_both:n_lo_block_lo:1": 0.589406, "S2:S_both:n_lo_block_lo:2": 0.480636, "S2:S_both:n_lo_block_lo:3": 0.614958, "S2:S_both:n_lo_block_lo:4": 0.641635, "S2:S_both:n_lo_block_lo:5": 0.335638, "S2:S_both:n_lo_block_lo:8": 0.281373, "S2:S_both:n_lo_burst:0": 0.219888, "S2:S_both:n_lo_burst:3": 0.514255, "S2:S_both:n_lo_burst:4": 0.348614, "S2:S_both:n_lo_burst:5": 0.812616, "S2:S_both:n_lo_burst:6": 0.902571, "S2:S_both:n_lo_burst:7": 0.645434, "S2:S_both:n_lo_burst:8": 0.657503, "S2:S_both:n_lo_full:0": 0.246749, "S2:S_both:n_lo_full:1": 0.539042, "S2:S_both:n_lo_full:2": 0.334685, "S2:S_both:n_lo_full:4": 0.337707, "S2:S_both:n_lo_full:5": 0.436823, "S2:S_both:n_lo_full:7": 0.363117, "S2:S_both:n_lo_full:8": 0.289906, "S2:S_both:n_lo_rand_hi:0": 0.249958, "S2:S_both:n_lo_rand_hi:1": 6.432659, "S2:S_both:n_lo_rand_hi:2": 0.498428, "S2:S_both:n_lo_rand_hi:3": 0.340612, "S2:S_both:n_lo_rand_hi:4": 0.781012, "S2:S_both:n_lo_rand_hi:5": 0.273249, "S2:S_both:n_lo_rand_hi:9": 0.347045, "S2:S_both:n_lo_rand_lo:1": 0.781184, "S2:S_both:n_lo_rand_lo:2": 3.952441, "S2:S_both:n_lo_rand_lo:5": 0.414561, "S2:S_both:n_lo_rand_lo:6": 0.911145, "S2:S_both:n_lo_rand_lo:7": 0.267832, "S2:S_both:n_lo_rand_lo:8": 1.170586, "S2:S_both:n_lo_rand_lo:9": 1.481481}}