{"domain": "S_intermittent", "action": "v_median", "model": "dlinear_pooled", "menu_sha": "a4c0f83191e5bd18fb8b7b9f52854e356268ef3cf0e7e3420e3a0221514db457", "train_cfg_sha": "812a71fdd8764baa", "n": 84, "n_missing": 0, "wallclock_s": 58.1, "cache_keys": {"S2:S_intermittent:n_hi_block_hi:2": "b7e714d8358d95e3"}, "per_series": {"S2:S_intermittent:n_hi_block_hi:2": 1.108359, "S2:S_intermittent:n_hi_block_hi:3": 1.015069, "S2:S_intermittent:n_hi_block_hi:4": 0.1668, "S2:S_intermittent:n_hi_block_hi:5": 1.059222, "S2:S_intermittent:n_hi_block_hi:6": 1.029189, "S2:S_intermittent:n_hi_block_hi:8": 0.999554, "S2:S_intermittent:n_hi_block_hi:9": 1.147403, "S2:S_intermittent:n_hi_block_lo:0": 1.083471, "S2:S_intermittent:n_hi_block_lo:2": 1.161279, "S2:S_intermittent:n_hi_block_lo:5": 0.981934, "S2:S_intermittent:n_hi_block_lo:6": 1.034323, "S2:S_intermittent:n_hi_block_lo:7": 1.007264, "S2:S_intermittent:n_hi_block_lo:8": 1.012285, "S2:S_intermittent:n_hi_block_lo:9": 1.000711, "S2:S_intermittent:n_hi_burst:0": 0.999014, "S2:S_intermittent:n_hi_burst:1": 1.023341, "S2:S_intermittent:n_hi_burst:2": 1.033862, "S2:S_intermittent:n_hi_burst:5": 1.010557, "S2:S_intermittent:n_hi_burst:7": 1.002262, "S2:S_intermittent:n_hi_burst:8": 0.126991, "S2:S_intermittent:n_hi_burst:9": 1.047076, "S2:S_intermittent:n_hi_full:0": 1.114169, "S2:S_intermittent:n_hi_full:2": 1.035701, "S2:S_intermittent:n_hi_full:3": 0.98739, "S2:S_intermittent:n_hi_full:4": 1.049306, "S2:S_intermittent:n_hi_full:5": 1.032431, "S2:S_intermittent:n_hi_full:6": 1.015705, "S2:S_intermittent:n_hi_full:7": 0.162293, "S2:S_intermittent:n_hi_rand_hi:0": 1.040143, "S2:S_intermittent:n_hi_rand_hi:1": 1.102568, "S2:S_intermittent:n_hi_rand_hi:2": 1.110019, "S2:S_intermittent:n_hi_rand_hi:4": 1.006071, "S2:S_intermittent:n_hi_rand_hi:6": 1.100703, "S2:S_intermittent:n_hi_rand_hi:7": 1.151195, "S2:S_intermittent:n_hi_rand_hi:9": 0.998625, "S2:S_intermittent:n_hi_rand_lo:0": 1.0126, "S2:S_intermittent:n_hi_rand_lo:1": 1.005375, "S2:S_intermittent:n_hi_rand_lo:2": 1.004123, "S2:S_intermittent:n_hi_rand_lo:5": 0.99829, "S2:S_intermittent:n_hi_rand_lo:7": 1.058253, "S2:S_intermittent:n_hi_rand_lo:8": 1.103614, "S2:S_intermittent:n_hi_rand_lo:9": 0.995882, "S2:S_intermittent:n_lo_block_hi:0": 1.111798, "S2:S_intermittent:n_lo_block_hi:1": 1.05094, "S2:S_intermittent:n_lo_block_hi:5": 1.015718, "S2:S_intermittent:n_lo_block_hi:6": 1.007748, "S2:S_intermittent:n_lo_block_hi:7": 1.16238, "S2:S_intermittent:n_lo_block_hi:8": 2.991756, "S2:S_intermittent:n_lo_block_hi:9": 1.046864, "S2:S_intermittent:n_lo_block_lo:0": 1.054224, "S2:S_intermittent:n_lo_block_lo:1": 1.193811, "S2:S_intermittent:n_lo_block_lo:2": 1.028354, "S2:S_intermittent:n_lo_block_lo:5": 0.989149, "S2:S_intermittent:n_lo_block_lo:6": 1.01905, "S2:S_intermittent:n_lo_block_lo:7": 1.03007, "S2:S_intermittent:n_lo_block_lo:8": 1.009851, "S2:S_intermittent:n_lo_burst:0": 1.058886, "S2:S_intermittent:n_lo_burst:2": 1.024341, "S2:S_intermittent:n_lo_burst:3": 0.992673, "S2:S_intermittent:n_lo_burst:6": 1.080297, "S2:S_intermittent:n_lo_burst:7": 1.013743, "S2:S_intermittent:n_lo_burst:8": 1.249558, "S2:S_intermittent:n_lo_burst:9": 1.212801, "S2:S_intermittent:n_lo_full:0": 1.002259, "S2:S_intermittent:n_lo_full:1": 1.008239, "S2:S_intermittent:n_lo_full:2": 1.061274, "S2:S_intermittent:n_lo_full:4": 1.006738, "S2:S_intermittent:n_lo_full:6": 1.132291, "S2:S_intermittent:n_lo_full:7": 1.03143, "S2:S_intermittent:n_lo_full:8": 1.047224, "S2:S_intermittent:n_lo_rand_hi:1": 1.011133, "S2:S_intermittent:n_lo_rand_hi:2": 1.071016, "S2:S_intermittent:n_lo_rand_hi:3": 1.075204, "S2:S_intermittent:n_lo_rand_hi:4": 1.04446, "S2:S_intermittent:n_lo_rand_hi:7": 0.99825, "S2:S_intermittent:n_lo_rand_hi:8": 1.000772, "S2:S_intermittent:n_lo_rand_hi:9": 1.12612, "S2:S_intermittent:n_lo_rand_lo:0": 1.044915, "S2:S_intermittent:n_lo_rand_lo:1": 1.12461, "S2:S_intermittent:n_lo_rand_lo:3": 1.084788, "S2:S_intermittent:n_lo_rand_lo:4": 1.271325, "S2:S_intermittent:n_lo_rand_lo:6": 1.05214, "S2:S_intermittent:n_lo_rand_lo:7": 1.048142, "S2:S_intermittent:n_lo_rand_lo:9": 1.033008}}