{
  "metadata": {
    "api_calls": 0,
    "composer": "deterministic_stub_no_api_composer",
    "n_records": 4,
    "raw_action": "v_none",
    "raw_action_semantics": "v_none_is_impute_linear_baseline_not_strict_raw",
    "reporter": "synthetic_oracle_proxy_v1",
    "slice": "synthetic_forecast_small"
  },
  "schema": "fast_path_ablation_report_v1",
  "slow_path": {
    "accepted_kind_counts": {
      "MemoryWrite": 1,
      "ProposeRiskRule": 1
    },
    "min_support": 2,
    "n_cells": 2,
    "n_promotion_accepted": 2,
    "n_proposals": 2,
    "proposal_kind_counts": {
      "MemoryWrite": 1,
      "ProposeRiskRule": 1
    },
    "schema": "fast_path_ablation_slow_path_summary_v1"
  },
  "summary": {
    "arm_order": [
      "raw",
      "deterministic_router",
      "skill_only_deterministic",
      "memory_only_selector",
      "skill_memory_deterministic",
      "composer_skill",
      "composer_skill_memory",
      "composer_skill_memory_safety"
    ],
    "arms": {
      "composer_skill": {
        "action_counts": {
          "v_median": 2,
          "v_none": 2
        },
        "composer_called": 4,
        "executed": 4,
        "mean_harm_delta_vs_raw": 0.0,
        "mean_lift_vs_raw_arm": -0.000156154771,
        "mean_role_b_score": 0.99982145232,
        "mean_utility_delta_vs_raw": 0.031588012075,
        "n": 4,
        "passed": 4,
        "raw_fallback": 0,
        "safety_reason_counts": {},
        "safety_rejected": 0,
        "status_counts": {
          "executed": 4
        }
      },
      "composer_skill_memory": {
        "action_counts": {
          "v_median": 4
        },
        "composer_called": 4,
        "executed": 4,
        "mean_harm_delta_vs_raw": 0.000156154771,
        "mean_lift_vs_raw_arm": -0.000312309543,
        "mean_role_b_score": 0.999662799563,
        "mean_utility_delta_vs_raw": 0.031431857304,
        "n": 4,
        "passed": 2,
        "raw_fallback": 0,
        "safety_reason_counts": {},
        "safety_rejected": 0,
        "status_counts": {
          "executed": 4
        }
      },
      "composer_skill_memory_safety": {
        "action_counts": {
          "v_median": 4
        },
        "composer_called": 4,
        "executed": 4,
        "mean_harm_delta_vs_raw": 0.000156154771,
        "mean_lift_vs_raw_arm": -0.000312309543,
        "mean_role_b_score": 0.999662799563,
        "mean_utility_delta_vs_raw": 0.031431857304,
        "n": 4,
        "passed": 2,
        "raw_fallback": 0,
        "safety_reason_counts": {},
        "safety_rejected": 0,
        "status_counts": {
          "executed": 4
        }
      },
      "deterministic_router": {
        "action_counts": {
          "v_median": 2,
          "v_none": 2
        },
        "composer_called": 0,
        "executed": 4,
        "mean_harm_delta_vs_raw": 0.0,
        "mean_lift_vs_raw_arm": -0.000156154771,
        "mean_role_b_score": 0.99982145232,
        "mean_utility_delta_vs_raw": 0.031588012075,
        "n": 4,
        "passed": 4,
        "raw_fallback": 0,
        "safety_reason_counts": {},
        "safety_rejected": 0,
        "status_counts": {
          "executed": 4
        }
      },
      "memory_only_selector": {
        "action_counts": {
          "v_median": 4
        },
        "composer_called": 4,
        "executed": 4,
        "mean_harm_delta_vs_raw": 0.000156154771,
        "mean_lift_vs_raw_arm": -0.000312309543,
        "mean_role_b_score": 0.999662799563,
        "mean_utility_delta_vs_raw": 0.031431857304,
        "n": 4,
        "passed": 2,
        "raw_fallback": 0,
        "safety_reason_counts": {},
        "safety_rejected": 0,
        "status_counts": {
          "executed": 4
        }
      },
      "raw": {
        "action_counts": {
          "v_none": 4
        },
        "composer_called": 0,
        "executed": 4,
        "mean_harm_delta_vs_raw": 0.0,
        "mean_lift_vs_raw_arm": 0.0,
        "mean_role_b_score": 1.0,
        "mean_utility_delta_vs_raw": 0.031744166847,
        "n": 4,
        "passed": 4,
        "raw_fallback": 0,
        "safety_reason_counts": {},
        "safety_rejected": 0,
        "status_counts": {
          "executed": 4
        }
      },
      "skill_memory_deterministic": {
        "action_counts": {
          "v_median": 2,
          "v_none": 2
        },
        "composer_called": 0,
        "executed": 4,
        "mean_harm_delta_vs_raw": 0.0,
        "mean_lift_vs_raw_arm": -0.000156154771,
        "mean_role_b_score": 0.99982145232,
        "mean_utility_delta_vs_raw": 0.031588012075,
        "n": 4,
        "passed": 4,
        "raw_fallback": 0,
        "safety_reason_counts": {},
        "safety_rejected": 0,
        "status_counts": {
          "executed": 4
        }
      },
      "skill_only_deterministic": {
        "action_counts": {
          "v_median": 2,
          "v_none": 2
        },
        "composer_called": 0,
        "executed": 4,
        "mean_harm_delta_vs_raw": 0.0,
        "mean_lift_vs_raw_arm": -0.000156154771,
        "mean_role_b_score": 0.99982145232,
        "mean_utility_delta_vs_raw": 0.031588012075,
        "n": 4,
        "passed": 4,
        "raw_fallback": 0,
        "safety_reason_counts": {},
        "safety_rejected": 0,
        "status_counts": {
          "executed": 4
        }
      }
    },
    "lift_metric": "utility_delta_vs_raw - raw_arm.utility_delta_vs_raw for same uid",
    "n_results": 32,
    "reference_arm": "raw",
    "reference_metric": "utility_delta_vs_raw",
    "schema": "fast_path_ablation_summary_v1"
  }
}