{
 "n": 666,
 "probes": [
  "v_median",
  "f0_median_w25",
  "v_stl"
 ],
 "per_dim": {
  "v_median": {
   "spearman": 0.1046,
   "spearman_p": 0.006879722103385372,
   "pearson": 0.0533,
   "sig_std": 0.1139,
   "oracle_std": 0.6914
  },
  "f0_median_w25": {
   "spearman": 0.2844,
   "spearman_p": 7.381196682033472e-14,
   "pearson": 0.2403,
   "sig_std": 0.2198,
   "oracle_std": 0.8409
  },
  "v_stl": {
   "spearman": -0.023,
   "spearman_p": 0.5528662030228045,
   "pearson": 0.0301,
   "sig_std": 0.0903,
   "oracle_std": 0.8482
  }
 },
 "family_separability": {
  "acc_1nn_signature": 0.3498,
  "acc_1nn_oracle_response": 0.4655,
  "acc_1nn_oracle_response_full9": 0.5841,
  "scatter_ratio_signature": 0.7586,
  "scatter_ratio_oracle": 0.9515,
  "scatter_ratio_oracle_full9": 0.9275,
  "note": "oracle 响应=评估专用上界；策略输入非法（prereg §0.1）"
 }
}